LICENSE
MANIFEST.in
README.md
setup.py
node_distance_ray/__init__.py
node_distance_ray/distances.py
node_distance_ray/distributions.py
node_distance_ray.egg-info/PKG-INFO
node_distance_ray.egg-info/SOURCES.txt
node_distance_ray.egg-info/dependency_links.txt
node_distance_ray.egg-info/requires.txt
node_distance_ray.egg-info/top_level.txt
node_distance_ray.egg-info/zip-safe
test/__init__.py
test/speedtest.py
test/test_.py