Metadata-Version: 2.1
Name: node-distance-ray
Version: 0.1.0
Summary: ray.io wrapper for node-distance package
Home-page: http://github.com/satzbeleg/node-distance-ray
Author: Ulf Hamster
Author-email: 554c46@gmail.com
License: Apache License 2.0
Platform: UNKNOWN
Requires-Python: >=3.6
License-File: LICENSE
